jupyterlab_eventlistener/__init__.py
jupyterlab_eventlistener/_version.py
jupyterlab_eventlistener-0.1.3.data/data/share/jupyter/labextensions/jupyterlab-eventlistener/package.json
jupyterlab_eventlistener-0.1.3.data/data/share/jupyter/labextensions/jupyterlab-eventlistener/static/728.859a9594f2847da63699.js
jupyterlab_eventlistener-0.1.3.data/data/share/jupyter/labextensions/jupyterlab-eventlistener/static/753.00e16c980310a36fa3b3.js
jupyterlab_eventlistener-0.1.3.data/data/share/jupyter/labextensions/jupyterlab-eventlistener/static/remoteEntry.d68977ae5a35080b44e4.js
jupyterlab_eventlistener-0.1.3.data/data/share/jupyter/labextensions/jupyterlab-eventlistener/static/style.js
jupyterlab_eventlistener-0.1.3.data/data/share/jupyter/labextensions/jupyterlab-eventlistener/static/third-party-licenses.json
jupyterlab_eventlistener-0.1.3.data/data/share/jupyter/labextensions/jupyterlab-eventlistener/install.json
jupyterlab_eventlistener-0.1.3.dist-info/METADATA
jupyterlab_eventlistener-0.1.3.dist-info/WHEEL
jupyterlab_eventlistener-0.1.3.dist-info/licenses/LICENSE
jupyterlab_eventlistener-0.1.3.dist-info/RECORD
