Metadata-Version: 2.4
Name: jupyterlab_eventlistener
Version: 0.1.3
Summary: A JupyterLab Plugin for listening to Jupyter events in the frontend.
Project-URL: Homepage, https://github.com/Zsailer/jupyterlab-eventlistener
Project-URL: Bug Tracker, https://github.com/Zsailer/jupyterlab-eventlistener/issues
Project-URL: Repository, https://github.com/Zsailer/jupyterlab-eventlistener.git
Author-email: Zach Sailer <zachsailer@gmail.com>
License: BSD 3-Clause License
License-File: LICENSE
Keywords: jupyter,jupyterlab,jupyterlab-extension
Classifier: Framework :: Jupyter
Classifier: Framework :: Jupyter :: JupyterLab
Classifier: Framework :: Jupyter :: JupyterLab :: 4
Classifier: Framework :: Jupyter :: JupyterLab :: Extensions
Classifier: Framework :: Jupyter :: JupyterLab :: Extensions :: Prebuilt
Classifier: License :: OSI Approved :: BSD License
Classifier: Programming Language :: Python
Classifier: Programming Language :: Python :: 3
Classifier: Programming Language :: Python :: 3.8
Classifier: Programming Language :: Python :: 3.9
Classifier: Programming Language :: Python :: 3.10
Classifier: Programming Language :: Python :: 3.11
Classifier: Programming Language :: Python :: 3.12
Requires-Python: >=3.8
